cacheit/__init__.py
cacheit/cache.py
cacheit-0.0.3.dist-info/LICENSE
cacheit-0.0.3.dist-info/METADATA
cacheit-0.0.3.dist-info/WHEEL
cacheit-0.0.3.dist-info/top_level.txt
cacheit-0.0.3.dist-info/zip-safe
cacheit-0.0.3.dist-info/RECORD
